Workbook

Sheet 요약
A1: NETS(ACOM) 라벨저울 – 스페인어권 비유럽 수입상/유통사 리스트
A2: 조사일: 2026-10-08 · 웹 검색 결과 기반 (업체 사이트 직접 접속 불가) – 연락 전 반드시 최신 연락처 재확인
A4: 우선순위 기준
A5: A | B5: 1차 컨택 – 라벨저울 판매 중 + 멀티브랜드/전환 가능
A6: B | B6: 2차 – 관련 채널이나 브랜드 묶임·정보 부족
A7: C | B7: 참고 – 서비스업체, 경쟁사 전속, 미검증
A9: 국가별 집계
A10: 국가 | B10: 전체 | C10: A | D10: B | E10: C | F10: 이메일 보유
A11: 멕시코 | B11: =COUNTIF('바이어 리스트'!$C$2:$C$106,A11) -> 12 | C11: =COUNTIFS('바이어 리스트'!$C$2:$C$106,$A11,'바이어 리스트'!$B$2:$B$106,"A") -> 3 | D11: =COUNTIFS('바이어 리스트'!$C$2:$C$106,$A11,'바이어 리스트'!$B$2:$B$106,"B") -> 5 | E11: =COUNTIFS('바이어 리스트'!$C$2:$C$106,$A11,'바이어 리스트'!$B$2:$B$106,"C") -> 4 | F11: =COUNTIFS('바이어 리스트'!$C$2:$C$106,A11,'바이어 리스트'!$G$2:$G$106,"*@*") -> 12
A12: 과테말라 | B12: =COUNTIF('바이어 리스트'!$C$2:$C$106,A12) -> 5 | C12: =COUNTIFS('바이어 리스트'!$C$2:$C$106,$A12,'바이어 리스트'!$B$2:$B$106,"A") -> 1 | D12: =COUNTIFS('바이어 리스트'!$C$2:$C$106,$A12,'바이어 리스트'!$B$2:$B$106,"B") -> 3 | E12: =COUNTIFS('바이어 리스트'!$C$2:$C$106,$A12,'바이어 리스트'!$B$2:$B$106,"C") -> 1 | F12: =COUNTIFS('바이어 리스트'!$C$2:$C$106,A12,'바이어 리스트'!$G$2:$G$106,"*@*") -> 5
A13: 엘살바도르 | B13: =COUNTIF('바이어 리스트'!$C$2:$C$106,A13) -> 3 | C13: =COUNTIFS('바이어 리스트'!$C$2:$C$106,$A13,'바이어 리스트'!$B$2:$B$106,"A") -> 1 | D13: =COUNTIFS('바이어 리스트'!$C$2:$C$106,$A13,'바이어 리스트'!$B$2:$B$106,"B") -> 2 | E13: =COUNTIFS('바이어 리스트'!$C$2:$C$106,$A13,'바이어 리스트'!$B$2:$B$106,"C") -> 0 | F13: =COUNTIFS('바이어 리스트'!$C$2:$C$106,A13,'바이어 리스트'!$G$2:$G$106,"*@*") -> 3
A14: 온두라스 | B14: =COUNTIF('바이어 리스트'!$C$2:$C$106,A14) -> 6 | C14: =COUNTIFS('바이어 리스트'!$C$2:$C$106,$A14,'바이어 리스트'!$B$2:$B$106,"A") -> 2 | D14: =COUNTIFS('바이어 리스트'!$C$2:$C$106,$A14,'바이어 리스트'!$B$2:$B$106,"B") -> 2 | E14: =COUNTIFS('바이어 리스트'!$C$2:$C$106,$A14,'바이어 리스트'!$B$2:$B$106,"C") -> 2 | F14: =COUNTIFS('바이어 리스트'!$C$2:$C$106,A14,'바이어 리스트'!$G$2:$G$106,"*@*") -> 5
A15: 니카라과 | B15: =COUNTIF('바이어 리스트'!$C$2:$C$106,A15) -> 3 | C15: =COUNTIFS('바이어 리스트'!$C$2:$C$106,$A15,'바이어 리스트'!$B$2:$B$106,"A") -> 1 | D15: =COUNTIFS('바이어 리스트'!$C$2:$C$106,$A15,'바이어 리스트'!$B$2:$B$106,"B") -> 1 | E15: =COUNTIFS('바이어 리스트'!$C$2:$C$106,$A15,'바이어 리스트'!$B$2:$B$106,"C") -> 1 | F15: =COUNTIFS('바이어 리스트'!$C$2:$C$106,A15,'바이어 리스트'!$G$2:$G$106,"*@*") -> 3
A16: 코스타리카 | B16: =COUNTIF('바이어 리스트'!$C$2:$C$106,A16) -> 5 | C16: =COUNTIFS('바이어 리스트'!$C$2:$C$106,$A16,'바이어 리스트'!$B$2:$B$106,"A") -> 2 | D16: =COUNTIFS('바이어 리스트'!$C$2:$C$106,$A16,'바이어 리스트'!$B$2:$B$106,"B") -> 2 | E16: =COUNTIFS('바이어 리스트'!$C$2:$C$106,$A16,'바이어 리스트'!$B$2:$B$106,"C") -> 1 | F16: =COUNTIFS('바이어 리스트'!$C$2:$C$106,A16,'바이어 리스트'!$G$2:$G$106,"*@*") -> 4
A17: 파나마 | B17: =COUNTIF('바이어 리스트'!$C$2:$C$106,A17) -> 5 | C17: =COUNTIFS('바이어 리스트'!$C$2:$C$106,$A17,'바이어 리스트'!$B$2:$B$106,"A") -> 1 | D17: =COUNTIFS('바이어 리스트'!$C$2:$C$106,$A17,'바이어 리스트'!$B$2:$B$106,"B") -> 2 | E17: =COUNTIFS('바이어 리스트'!$C$2:$C$106,$A17,'바이어 리스트'!$B$2:$B$106,"C") -> 2 | F17: =COUNTIFS('바이어 리스트'!$C$2:$C$106,A17,'바이어 리스트'!$G$2:$G$106,"*@*") -> 5
A18: 콜롬비아 | B18: =COUNTIF('바이어 리스트'!$C$2:$C$106,A18) -> 8 | C18: =COUNTIFS('바이어 리스트'!$C$2:$C$106,$A18,'바이어 리스트'!$B$2:$B$106,"A") -> 2 | D18: =COUNTIFS('바이어 리스트'!$C$2:$C$106,$A18,'바이어 리스트'!$B$2:$B$106,"B") -> 5 | E18: =COUNTIFS('바이어 리스트'!$C$2:$C$106,$A18,'바이어 리스트'!$B$2:$B$106,"C") -> 1 | F18: =COUNTIFS('바이어 리스트'!$C$2:$C$106,A18,'바이어 리스트'!$G$2:$G$106,"*@*") -> 7
A19: 에콰도르 | B19: =COUNTIF('바이어 리스트'!$C$2:$C$106,A19) -> 6 | C19: =COUNTIFS('바이어 리스트'!$C$2:$C$106,$A19,'바이어 리스트'!$B$2:$B$106,"A") -> 1 | D19: =COUNTIFS('바이어 리스트'!$C$2:$C$106,$A19,'바이어 리스트'!$B$2:$B$106,"B") -> 2 | E19: =COUNTIFS('바이어 리스트'!$C$2:$C$106,$A19,'바이어 리스트'!$B$2:$B$106,"C") -> 3 | F19: =COUNTIFS('바이어 리스트'!$C$2:$C$106,A19,'바이어 리스트'!$G$2:$G$106,"*@*") -> 6
A20: 도미니카공화국 | B20: =COUNTIF('바이어 리스트'!$C$2:$C$106,A20) -> 4 | C20: =COUNTIFS('바이어 리스트'!$C$2:$C$106,$A20,'바이어 리스트'!$B$2:$B$106,"A") -> 1 | D20: =COUNTIFS('바이어 리스트'!$C$2:$C$106,$A20,'바이어 리스트'!$B$2:$B$106,"B") -> 3 | E20: =COUNTIFS('바이어 리스트'!$C$2:$C$106,$A20,'바이어 리스트'!$B$2:$B$106,"C") -> 0 | F20: =COUNTIFS('바이어 리스트'!$C$2:$C$106,A20,'바이어 리스트'!$G$2:$G$106,"*@*") -> 4
A21: 베네수엘라 | B21: =COUNTIF('바이어 리스트'!$C$2:$C$106,A21) -> 6 | C21: =COUNTIFS('바이어 리스트'!$C$2:$C$106,$A21,'바이어 리스트'!$B$2:$B$106,"A") -> 0 | D21: =COUNTIFS('바이어 리스트'!$C$2:$C$106,$A21,'바이어 리스트'!$B$2:$B$106,"B") -> 5 | E21: =COUNTIFS('바이어 리스트'!$C$2:$C$106,$A21,'바이어 리스트'!$B$2:$B$106,"C") -> 1 | F21: =COUNTIFS('바이어 리스트'!$C$2:$C$106,A21,'바이어 리스트'!$G$2:$G$106,"*@*") -> 6
A22: 푸에르토리코 | B22: =COUNTIF('바이어 리스트'!$C$2:$C$106,A22) -> 3 | C22: =COUNTIFS('바이어 리스트'!$C$2:$C$106,$A22,'바이어 리스트'!$B$2:$B$106,"A") -> 0 | D22: =COUNTIFS('바이어 리스트'!$C$2:$C$106,$A22,'바이어 리스트'!$B$2:$B$106,"B") -> 1 | E22: =COUNTIFS('바이어 리스트'!$C$2:$C$106,$A22,'바이어 리스트'!$B$2:$B$106,"C") -> 2 | F22: =COUNTIFS('바이어 리스트'!$C$2:$C$106,A22,'바이어 리스트'!$G$2:$G$106,"*@*") -> 3
... A28: 파라과이 | B28: =COUNTIF('바이어 리스트'!$C$2:$C$106,A28) -> 4 | C28: =COUNTIFS('바이어 리스트'!$C$2:$C$106,$A28,'바이어 리스트'!$B$2:$B$106,"A") -> 2 | D28: =COUNTIFS('바이어 리스트'!$C$2:$C$106,$A28,'바이어 리스트'!$B$2:$B$106,"B") -> 0 | E28: =COUNTIFS('바이어 리스트'!$C$2:$C$106,$A28,'바이어 리스트'!$B$2:$B$106,"C") -> 2 | F28: =COUNTIFS('바이어 리스트'!$C$2:$C$106,A28,'바이어 리스트'!$G$2:$G$106,"*@*") -> 4
A29: 합계 | B29: =SUM(B11:B28) -> 105 | C29: =SUM(C11:C28) -> 28 | D29: =SUM(D11:D28) -> 46 | E29: =SUM(E11:E28) -> 31 | F29: =SUM(F11:F28) -> 101
A31: 메일 발송: '메일 발송용' 시트(이메일 1개당 1행, 메일머지용). 영업 진행 기록: '바이어 리스트' 시트 오른쪽 노란색 열(컨택일/상태/담당자/메모)에 직접 입력하세요. 상태는 드롭다운 선택.

Sheet 메일 발송용
A1: 우선순위 | B1: 국가 | C1: 회사명 | D1: 이메일 | E1: 대표 주소 여부
A2: A | B2: 과테말라 | C2: Inter-Americana | D2: ventas@inter-americana.com | E2: 대표
A3: A | B3: 니카라과 | C3: Azocar Nicaragua | D3: info@azocarnicaragua.com | E3: 대표
A4: A | B4: 도미니카공화국 | C4: Serpoca | D4: ventas@serpoca.com.do | E4: 대표
A5: A | B5: 도미니카공화국 | C5: Serpoca | D5: info@serpoca.com.do
A6: A | B6: 멕시코 | C6: Noscom | D6: contacto@noscom.mx | E6: 대표
A7: A | B7: 멕시코 | C7: Básculas Mexicanas S.A. de C.V. (Básculas IBN) | D7: ventas@basculasibn.com | E7: 대표
A8: A | B8: 멕시코 | C8: Rhino Maquinaria S.A. de C.V. | D8: info@rhino.mx | E8: 대표
A9: A | B9: 볼리비아 | C9: CAS – Computer & Sensors SRL | D9: info@cas-bo.com | E9: 대표
A10: A | B10: 볼리비아 | C10: CAS – Computer & Sensors SRL | D10: ventas@cas-bo.com
A11: A | B11: 볼리비아 | C11: Exim SRL | D11: info@exim.com.bo | E11: 대표
A12: A | B12: 아르헨티나 | C12: Grupo Hasar (Hasar Sistemas SRL) | D12: info@hasar.com | E12: 대표
A13: A | B13: 에콰도르 | C13: La Competencia S.A. | D13: ventas@competencia.com.ec | E13: 대표
A14: A | B14: 에콰도르 | C14: La Competencia S.A. | D14: marketing@competencia.com.ec
A15: A | B15: 엘살바도르 | C15: Puntos de Venta El Salvador | D15: info@puntosdeventa.com.sv | E15: 대표
A16: A | B16: 온두라스 | C16: IMERCO Honduras | D16: ventas@imercohn.net | E16: 대표
A17: A | B17: 온두라스 | C17: Inter-Americana Honduras | D17: ventashn@inter-americana.com | E17: 대표
A18: A | B18: 우루과이 | C18: Baudin Equipamientos | D18: ventas@baudinequipamientos.com | E18: 대표
A19: A | B19: 우루과이 | C19: Baudin Equipamientos | D19: gerencia@baudinequipamientos.com
A20: A | B20: 우루과이 | C20: Ser-Tec | D20: ventas@ser-tec.com.uy | E20: 대표
A21: A | B21: 우루과이 | C21: Ser-Tec | D21: info@ser-tec.com.uy
A22: A | B22: 칠레 | C22: Tecno Rebas | D22: ventas@tecnorebas.cl | E22: 대표
A23: A | B23: 칠레 | C23: Ing Métrica SpA | D23: contacto@ingmetrica.cl | E23: 대표
A24: A | B24: 칠레 | C24: Balanzas.cl | D24: contacto@balanzas.cl | E24: 대표
A25: A | B25: 코스타리카 | C25: Nexius | D25: eguerrero@nexius.tools | E25: 대표
A26: A | B26: 코스타리카 | C26: Nexius | D26: melramos@nexius.tools
A27: A | B27: 코스타리카 | C27: Romanas Azocar | D27: info@azocarcr.com | E27: 대표
A28: A | B28: 콜롬비아 | C28: BBG Colombia SAS (Básculas y Balanzas Guadalupe) | D28: ventas@basculasbbg.com | E28: 대표
A29: A | B29: 콜롬비아 | C29: BBG Colombia SAS (Básculas y Balanzas Guadalupe) | D29: distribuidoresmedellin@basculasbbg.com
A30: A | B30: 콜롬비아 | C30: BBG Colombia SAS (Básculas y Balanzas Guadalupe) | D30: medellin@basculasbbg.com
A31: A | B31: 콜롬비아 | C31: BBG Colombia SAS (Básculas y Balanzas Guadalupe) | D31: info@basculasbbg.com
A32: A | B32: 콜롬비아 | C32: Badecol (Balanzas de Colombia) | D32: ventas@badecol.com | E32: 대표
A33: A | B33: 콜롬비아 | C33: Badecol (Balanzas de Colombia) | D33: comercial@badecol.com
A34: A | B34: 콜롬비아 | C34: Badecol (Balanzas de Colombia) | D34: exportaciones@badecol.com
A35: A | B35: 파나마 | C35: STH Panamá | D35: ventas@sthpanama.com | E35: 대표
A36: A | B36: 파라과이 | C36: Balanzas Paraguayas S.A. (Balpar) | D36: licitaciones@balpar.com.py | E36: 대표
A37: A | B37: 파라과이 | C37: HPTI Sistemas y Equipamientos | D37: licitaciones@hpti.com.py | E37: 대표
A38: A | B38: 페루 | C38: Gufra Perú | D38: ventas@gufraperu.com | E38: 대표
A39: A | B39: 페루 | C39: Gufra Perú | D39: administracion@gufraperu.com
A40: A | B40: 페루 | C40: Invercorp Perú | D40: ventas@invercorp-peru.com | E40: 대표
A41: A | B41: 페루 | C41: Miyake | D41: info@miyake.com.pe | E41: 대표
A42: A | B42: 페루 | C42: Miyake | D42: asistente@miyake.com.pe
A43: B | B43: 과테말라 | C43: Soluciones Exactas S.A. | D43: krosales@soluciones-exactas.com | E43: 대표
A44: B | B44: 과테말라 | C44: PKM Industrial S.A. | D44: administracion@pkm-gua.com | E44: 대표
A45: B | B45: 과테말라 | C45: Servitebb | D45: servicioespecializado@servitebb.com | E45: 대표
A46: B | B46: 니카라과 | C46: Servibásculas S.A. | D46: ventas@servibasculas.com | E46: 대표
A47: B | B47: 도미니카공화국 | C47: Baserna (Balanzas y Servicios Nacionales) | D47: serviciosbaserna@gmail.com | E47: 대표
A48: B | B48: 도미니카공화국 | C48: Balanzas Industriales S.R.L. | D48: info@balanzasindustriales.com | E48: 대표
A49: B | B49: 도미니카공화국 | C49: Balanzas Industriales S.R.L. | D49: asistente@balanzasindustriales.com
A50: B | B50: 도미니카공화국 | C50: Balanza Del Caribe | D50: balanzadelcaribe@gmail.com | E50: 대표
A51: B | B51: 멕시코 | C51: Microdatanorte / MR Tienda | D51: ventas@microdatanorte.com.mx | E51: 대표
A52: B | B52: 멕시코 | C52: Grupo Mexba | D52: ventas@mexba.com.mx | E52: 대표
A53: B | B53: 멕시코 | C53: Grupo Mexba | D53: gmexba@gmail.com
A54: B | B54: 멕시코 | C54: Asesoría Integral de Básculas (AIBSA) | D54: areacomercial@aibasculas.com | E54: 대표
A55: B | B55: 멕시코 | C55: Sistemas Digitales MX | D55: german.reyn@sistemas-digitales-mx.com | E55: 대표
A56: B | B56: 멕시코 | C56: Básculas Internacionales de México (BIM) | D56: ventas.tij@basculasint.com | E56: 대표
A57: B | B57: 베네수엘라 | C57: Xacta Servicios C.A. (Industrias Metarmes) | D57: balanzas@xacta.com.ve | E57: 대표
A58: B | B58: 베네수엘라 | C58: Hitech 2023 | D58: ventas@hitech2023.com | E58: 대표
A59: B | B59: 베네수엘라 | C59: Batvenca | D59: ventas@batvenca.com | E59: 대표
A60: B | B60: 베네수엘라 | C60: Balanzas Lara | D60: ventas@balanzaslara.com | E60: 대표
A61: B | B61: 베네수엘라 | C61: Balanzas Lara | D61: servicios@balanzaslara.com
A62: B | B62: 베네수엘라 | C62: Laser Print Soluciones | D62: ventas@laserprintsoluciones.com | E62: 대표
A63: B | B63: 베네수엘라 | C63: Laser Print Soluciones | D63: info@laserprintsoluciones.com
A64: B | B64: 볼리비아 | C64: Pesotodo SRL | D64: ventas@pesotodo.com | E64: 대표
A65: B | B65: 볼리비아 | C65: Zelada Precision SRL | D65: gzelada@zeladaprecision.com | E65: 대표
A66: B | B66: 아르헨티나 | C66: FDC Soluciones SRL | D66: info@fdcsoluciones.com | E66: 대표
A67: B | B67: 아르헨티나 | C67: Posvent | D67: info@posventar.com | E67: 대표
A68: B | B68: 아르헨티나 | C68: Balanzas Kyaserv | D68: info@kyaserv.com.ar | E68: 대표
A69: B | B69: 아르헨티나 | C69: Balanzas Kyaserv | D69: info@balanza.com.ar
A70: B | B70: 아르헨티나 | C70: Digital Crams | D70: info@dcrams.com.ar | E70: 대표
A71: B | B71: 아르헨티나 | C71: STEC Soluciones Tecnológicas | D71: ventas@stec.com.ar | E71: 대표
A72: B | B72: 에콰도르 | C72: Electrónica Casio | D72: ventasbalanzascas@electronicacasio.com.ec | E72: 대표
A73: B | B73: 에콰도르 | C73: Ingelsoft | D73: info@ingelsoft.com | E73: 대표
A74: B | B74: 엘살바도르 | C74: Básculas y Balanzas S.A. de C.V. | D74: info@basculasybalanzassv.com | E74: 대표
A75: B | B75: 엘살바도르 | C75: Exactos Equipos | D75: exactosequipos@gmail.com | E75: 대표
A76: B | B76: 온두라스 | C76: IPESAH | D76: cotizaciones@ipesah.com | E76: 대표
A77: B | B77: 온두라스 | C77: RR Inversiones | D77: info@rrinversiones.com | E77: 대표
A78: B | B78: 우루과이 | C78: Balanzas Larynco | D78: reparaciones@balanzaslarynco.com.uy | E78: 대표
A79: B | B79: 칠레 | C79: Precision (precision.tech) | D79: contactanos_chile@precision.tech | E79: 대표
A80: B | B80: 칠레 | C80: Maqequipos | D80: ventas@maq-equipos.cl | E80: 대표
A81: B | B81: 코스타리카 | C81: Reproma | D81: info@reproma.com | E81: 대표
... A83: B | B83: 콜롬비아 | C83: Básculas Bil | D83: basculasbil@gmail.com | E83: 대표
A84: B | B84: 콜롬비아 | C84: Básculas Bil | D84: basculasyequiposbil@gmail.com
A85: B | B85: 콜롬비아 | C85: Básculas Bil | D85: bilvalledupar@gmail.com
A86: B | B86: 콜롬비아 | C86: Distriequipos Bogotá | D86: ventas@distriequiposbogota.com | E86: 대표
A87: B | B87: 콜롬비아 | C87: Distriequipos Bogotá | D87: calidad@distriequiposbogota.com
A88: B | B88: 콜롬비아 | C88: Impoventas Colombia | D88: comercial1@impoventas.com.co | E88: 대표
A89: B | B89: 콜롬비아 | C89: Impoventas Colombia | D89: comercial2@impoventas.com.co
A90: B | B90: 콜롬비아 | C90: Impoventas Colombia | D90: info@impoventas.com.co
A91: B | B91: 파나마 | C91: Grupo Único Internacional (CPG Panamá) | D91: ventas@cpgpanama.com | E91: 대표
A92: B | B92: 파나마 | C92: Grupo Único Internacional (CPG Panamá) | D92: cpg507@outlook.com
A93: B | B93: 파나마 | C93: Posper Panamá | D93: ventas@posperpanama.com | E93: 대표
A94: B | B94: 파나마 | C94: Posper Panamá | D94: ventas2@posperpanama.com
A95: B | B95: 페루 | C95: La Casa de la Balanza Perú | D95: ventas@lacasadelabalanzaperu.com | E95: 대표
A96: B | B96: 페루 | C96: Balanzas Precisur | D96: ventas@balanzasprecisur.com | E96: 대표
A97: B | B97: 페루 | C97: Balanzas PE | D97: ventas@balanzas.pe | E97: 대표
A98: B | B98: 푸에르토리코 | C98: SSM Foodservice Equipment / Scale Food Equipment & Systems | D98: ssmfse@gmail.com | E98: 대표
A99: B | B99: 푸에르토리코 | C99: SSM Foodservice Equipment / Scale Food Equipment & Systems | D99: ssmhse@gmail.com
A100: C | B100: 과테말라 | C100: Probaza S.A. | D100: servicios@probazagt.com | E100: 대표
A101: C | B101: 니카라과 | C101: Básculas Rodríguez Nicaragua | D101: basculas.rodriguez@outlook.com | E101: 대표
...

Sheet 바이어 리스트
A1: No | B1: 우선순위 | C1: 국가 | D1: 회사명 | E1: 도시 | F1: 웹사이트 | G1: 이메일 | H1: 전화/WhatsApp | I1: 이메일 출처 | J1: 연락 메모 | K1: 취급 브랜드/제품 | L1: 유형 | M1: NETS 적합도 | N1: 적합 사유 | O1: 출처 URL | P1: 컨택일 | Q1: 상태 | R1: 담당자 | S1: 메모
A2: 1 | B2: A | C2: 멕시코 | D2: Noscom | E2: Tijuana / CDMX | F2: noscom.mx | G2: contacto@noscom.mx | H2: Tijuana (664) 647-5632; CDMX (55) 5208-8565; WA 663 208 8849 | I2: 기존 조사 (회사 사이트/디렉토리) | K2: SAM4s POS + CAS 라벨저울(CN1, CL5200/5500) | L2: 유통(POS+저울) | M2: 상 | N2: POS+라벨저울 번들 영업, 이미 한국 브랜드(CAS) 취급 → 한국산 대안 제안 용이 | O2: https://www.noscom.mx/
A3: 2 | B3: A | C3: 멕시코 | D3: Básculas Mexicanas S.A. de C.V. (Básculas IBN) | E3: Monterrey, NL | F3: basculasibn.com | G3: ventas@basculasibn.com | H3: +52 81 8129 6799 / 8129 6788; WA 81 8163 3310 | I3: 기존 조사 (회사 사이트/디렉토리) | K3: 슈퍼마켓용 라벨저울(자체 e-tikket), DIGI, 포션저울 | L3: 수입/딜러 | M3: 상 | N3: 슈퍼용 라벨저울 판매, 멀티브랜드, 한국 브랜드 없음 | O3: https://basculasibn.com/basculas-etiquetadoras/
A4: 3 | B4: A | C4: 멕시코 | D4: Rhino Maquinaria S.A. de C.V. | E4: Atizapán, Edo. Méx. | F4: rhino.mx | G4: info@rhino.mx | H4: (55) 4429 0229; 800 377 8242 | I4: 기존 조사 (회사 사이트/디렉토리) | K4: 자체 브랜드 Rhino(수입 OEM), BAET-30 라벨저울, 전국 서비스망 | L4: 브랜드 수입사 | M4: 중상 | N4: 아시아산 OEM 자체브랜드 운영 → NETS OEM/ODM 파트너 가능(동시에 경쟁사) | O4: https://www.rhino.mx/producto/bascula-etiquetadora-baet-30/
A5: 4 | B5: B | C5: 멕시코 | D5: Microdatanorte / MR Tienda | E5: Baja California, BCS | F5: microdatanorte.com.mx | G5: ventas@microdatanorte.com.mx | H5: 615 157 1230; WA 615 155 8228 | I5: 기존 조사 (회사 사이트/디렉토리) | K5: POS SW/HW + CAS 저울(CL5000/5500) | L5: POS 딜러 | M5: 중상 | N5: CAS 라벨저울 파는 POS 통합업체, 지역 한정 | O5: http://www.microdatanorte.com.mx/basculas/
A6: 5 | B6: B | C6: 멕시코 | D6: Grupo Mexba | E6: Estado de México (전국 서비스) | F6: mexba.com.mx | G6: ventas@mexba.com.mx; gmexba@gmail.com | I6: 기존 조사 (회사 사이트/디렉토리) | K6: DIGI 멕시코 독점 유통 표방(SM-120, SM-100H), 32개 주 서비스 | L6: 독점유통+서비스 | M6: 중 | N6: 소매저울 채널 강력하나 DIGI 묶임 → 세컨드/가격대 브랜드로 제안 | O6: https://mexba.com.mx/index.php
A7: 6 | B7: B | C7: 멕시코 | D7: Asesoría Integral de Básculas (AIBSA) | E7: Puebla | F7: aibasculas.com | G7: areacomercial@aibasculas.com | H7: (222) 220 3051 / 220 0267 / 213 1159 | I7: 기존 조사 (회사 사이트/디렉토리) | K7: CAS 등 판매·서비스 | L7: 딜러/서비스 | M7: 중 | N7: CAS 경험, 지역 업체 | O7: https://www.aibasculas.com/
A8: 7 | B8: B | C8: 멕시코 | D8: Sistemas Digitales MX | E8: Baja California | F8: sistemas-digitales-mx.com | G8: german.reyn@sistemas-digitales-mx.com | H8: 664 238 7690; 664 103 7186 | I8: sistemas-digitales-mx.com (메타데이터, 신뢰도 낮음) | K8: CAS CL-5200, CN1 + CL-Works | L8: 딜러 | M8: 중 | N8: 소규모 CAS 리셀러 | O8: https://sistemas-digitales-mx.com/bascula-electronica-digital-etiquetadora-cas-cl-5200/
A9: 8 | B9: B | C9: 멕시코 | D9: Básculas Internacionales de México (BIM) | E9: Tijuana, BC | G9: ventas.tij@basculasint.com | H9: 664 120 5997; (디렉토리) | I9: 기존 조사 (회사 사이트/디렉토리) | K9: 저울 전반, 전국 대리점망 | L9: 유통 | M9: 중 | N9: 전국 딜러망 (디렉토리 정보, 오래됐을 수 있음) | O9: https://construex.com.mx/exhibidores/basculas_internacionales_de_mexico_bim
A10: 9 | B10: C | C10: 멕시코 | D10: Cereco / Equipos Torrey | E10: CDMX, Puebla | F10: equipostorrey.com.mx | G10: info@cereco.com.mx | H10: 55-2898-3775; WA 55-2724-1542 | I10: 기존 조사 (회사 사이트/디렉토리) | K10: Torrey 라벨저울(W-Label), 주방설비 | L10: 딜러 | M10: 중하 | N10: Torrey 충성 딜러, 정육점·델리 판매 | O10: https://equipostorrey.com.mx/categoria-producto/pesaje/basculas-etiquetadoras/
A11: 10 | B11: C | C11: 멕시코 | D11: JL Rodríguez S.A. de C.V. | E11: Guadalajara | F11: jlrodriguez.com.mx | G11: contacto@jlrodriguez.com.mx; JLRODRIGUEZTR@gmail.com | H11: 33-3811-8047 / 8981 / 5348 | I11: jlrodriguez.com.mx/contacto; construex | J11: WA +52 33 2236 2702 | K11: Torrey 저울, 냉장설비 | L11: 딜러 | M11: 중하 | N11: Torrey 딜러 | O11: http://www.jlrodriguez.com.mx/productos-y-servicios
A12: 11 | B12: C | C12: 멕시코 | D12: Badimex | E12: Querétaro / CDMX | F12: badimex.mx | G12: info@badimex.mx | H12: (44) 2100-4813; WA (55) 6785-6352 | I12: 기존 조사 (회사 사이트/디렉토리) | K12: 디지털 저울, 업소용 기계 | L12: 딜러/소매 | M12: 중하 | N12: 라벨저울 취급 미확인 | O12: https://www.badimex.mx/
A13: 12 | B13: A | C13: 과테말라 | D13: Inter-Americana | E13: Guatemala City 외 (온두라스 지사) | F13: inter-americana.com | G13: ventas@inter-americana.com | H13: PBX (502) 2427-5000 | I13: 기존 조사 (회사 사이트/디렉토리) | K13: Torrey 라벨저울, 식품가공·정육 장비 | L13: 수입/유통 | M13: 상 | N13: GT+HN 정육·식품 소매에 라벨저울 판매, Torrey만 취급 | O13: https://www.inter-americana.com/pesaje
A14: 13 | B14: B | C14: 과테말라 | D14: Soluciones Exactas S.A. | E14: Guatemala (중미 커버) | F14: soluciones-exactas.com | G14: krosales@soluciones-exactas.com | H14: (502) 5968-5590; 2460-8068 | I14: 기존 조사 (회사 사이트/디렉토리) | K14: 멀티브랜드 산업/정밀/상업용 저울, 교정 | L14: 유통+서비스 | M14: 중상 | N14: 멀티브랜드 수입 + 교정 역량 | O14: https://www.soluciones-exactas.com/
A15: 14 | B15: B | C15: 과테말라 | D15: PKM Industrial S.A. | E15: Guatemala | F15: pkm-gua.com | G15: administracion@pkm-gua.com | H15: (502) 6633-9972; 2375-2147 | I15: pkm-gua.com | K15: Rice Lake, Dini Argeo, Sartorius | L15: 유통 | M15: 중 | N15: 산업용 중심, 상업용 벤치저울도 판매 | O15: https://www.pkm-gua.com/
A16: 15 | B16: B | C16: 과테말라 | D16: Servitebb | E16: Guatemala City | F16: servitebb.com | G16: servicioespecializado@servitebb.com | H16: WA +502 5039-5386 | I16: 기존 조사 (회사 사이트/디렉토리) | K16: 상업용·플랫폼·트럭 저울, 수리 | L16: 딜러/서비스 | M16: 중 | N16: 소매저울 판매+서비스 | O16: https://www.servitebb.com/
A17: 16 | B17: C | C17: 과테말라 | D17: Probaza S.A. | E17: Guatemala | F17: probazagt.com | G17: servicios@probazagt.com | H17: 2292-5397 | I17: 기존 조사 (회사 사이트/디렉토리) | K17: 교정/인증 (전 브랜드) | L17: 서비스 | M17: 중하 | N17: 수입사 아님, 서비스 파트너 | O17: https://www.probazagt.com/
A18: 17 | B18: A | C18: 엘살바도르 | D18: Puntos de Venta El Salvador | E18: Santa Tecla | F18: puntosdeventa.com.sv | G18: info@puntosdeventa.com.sv | H18: (503) 2556-6707 | I18: 기존 조사 (회사 사이트/디렉토리) | K18: POS HW(Zebra, Epson, Bixolon), 라벨프린터, 저울 | L18: POS 딜러 | M18: 중상 | N18: 저울 파는 POS 채널, 라벨저울 추가 가능 | O18: https://puntosdeventa.com.sv/
A19: 18 | B19: B | C19: 엘살바도르 | D19: Básculas y Balanzas S.A. de C.V. | E19: San Salvador | F19: basculasybalanzassv.com | G19: info@basculasybalanzassv.com | H19: +503 2521-7100 | I19: 기존 조사 (회사 사이트/디렉토리) | K19: CAS 공인/독점 유통(GT,HN,NI,SV), HAENNI, Rice Lake, 교정 | L19: 독점유통+서비스 | M19: 중 | N19: 중미 북부 CAS 메인 채널 – 묶여있을 수 있으나 전환 타깃 | O19: https://basculasybalanzassv.com/distribuidores-autorizados/
A20: 19 | B20: B | C20: 엘살바도르 | D20: Exactos Equipos | E20: San Salvador, San Miguel | F20: exactosequipos.com | G20: exactosequipos@gmail.com | H20: +503 7968-4778 | I20: facebook.com/exactoselsalvador/ | J20: FB 번호 +503 7740 0083 | K20: Rhino, Vinson(멕시코 브랜드) | L20: 딜러 | M20: 중 | N20: 지점망 보유, 라벨저울 브랜드 없음 | O20: https://exactosequipos.com/contacto
A21: 20 | B21: A | C21: 온두라스 | D21: IMERCO Honduras | E21: San Pedro Sula, Tegucigalpa | F21: imercohn.net | G21: ventas@imercohn.net | H21: PBX 3170-3521 | I21: 기존 조사 (회사 사이트/디렉토리) | K21: Torrey 라벨저울(W-LABEL) | L21: 유통 | M21: 상 | N21: 양대 도시에서 라벨저울 판매, Torrey만 취급 | O21: https://imercohn.net/pesaje/
A22: 21 | B22: A | C22: 온두라스 | D22: Inter-Americana Honduras | E22: San Pedro Sula | F22: inter-americana.com/honduras | G22: ventashn@inter-americana.com | H22: (504) 2508-2558 | I22: 기존 조사 (회사 사이트/디렉토리) | K22: Torrey 저울, 식품설비 | L22: 유통 | M22: 상 | N22: 과테말라 본사와 일괄 제안 | O22: https://www.inter-americana.com/honduras
A23: 22 | B23: B | C23: 온두라스 | D23: IPESAH | E23: San Pedro Sula | F23: ipesah.com | G23: cotizaciones@ipesah.com | H23: +504 2504-2016 | I23: 기존 조사 (회사 사이트/디렉토리) | K23: Rice Lake, Dini Argeo 공인, ISO17025 교정랩 | L23: 유통+서비스 | M23: 중 | N23: 서비스/교정 기반 강함, 소매 라벨저울 약함 | O23: https://ipesah.com/
A24: 23 | B24: C | C24: 온두라스 | D24: BABASE | E24: San Pedro Sula | G24: ventashn@babase.net; administracion@babase.net; servicioalcliente@babasehn.com | H24: 2550-0330 (오래된 디렉토리) | I24: babase.net/Contactenos.html; babasehn.com | J24: +504 2552-5091 / 2550-1636 | K24: 저울 공급·서비스 | L24: 딜러/서비스 | M24: 중하 | N24: 정보 오래됨 | O24: https://www.dehonduras.com/honduras/comercio-e-industria/basculas-y-balanzas.php
A25: 24 | B25: C | C25: 온두라스 | D25: F.A. Dalton S.A. de C.V. | E25: San Pedro Sula | H25: 551-3070 (디렉토리) | J25: 이메일 미공개 – Grupo DISAGRO 소속(Mettler 대리), disagro.com 문의폼 이용 | K25: 저울 판매·서비스·교정 | L25: 딜러/서비스 | M25: 하 | N25: 디렉토리 정보만 | O25: https://www.dehonduras.com/honduras/comercio-e-industria/basculas-y-balanzas.php
A26: 25 | B26: A | C26: 니카라과 | D26: Azocar Nicaragua | E26: Managua | F26: azocarnicaragua.com | G26: info@azocarnicaragua.com | H26: +505 7656-0710 / 2276-0215 | I26: 기존 조사 (회사 사이트/디렉토리) | K26: Hiweigh, Ishida, Kretz, CAS, Ohaus, Rice Lake, Datamax 등 | L26: 수입/유통 | M26: 상 | N26: 멀티브랜드 소매라인, 코스타리카 Azocar 자매사 | O26: https://azocarnicaragua.com/contactanos/
A27: 26 | B27: B | C27: 니카라과 | D27: Servibásculas S.A. | E27: Managua | F27: servibasculas.com | G27: ventas@servibasculas.com | H27: +505 2225-1968 | I27: 기존 조사 (회사 사이트/디렉토리) | K27: 티켓 프린트 저울, 방수저울, 설치·교정 | L27: 유통+서비스 | M27: 중상 | N27: 프린트 저울 이미 판매 | O27: https://www.servibasculas.com/
A28: 27 | B28: C | C28: 니카라과 | D28: Básculas Rodríguez Nicaragua | E28: Managua | F28: bascularodriguez.com | G28: basculas.rodriguez@outlook.com | H28: 2225-2409; 8724-6659 | I28: bascularodriguez.com; Facebook | J28: +505 7706 3501 | K28: 트럭저울, 인디케이터, 교정 | L28: 딜러/서비스 | M28: 하 | N28: 산업용 중심 | O28: https://bascularodriguez.com/
A29: 28 | B29: A | C29: 코스타리카 | D29: Nexius | E29: Costa Rica | F29: nexius.tools | G29: eguerrero@nexius.tools; melramos@nexius.tools | H29: WA +506 8873-5883 | I29: nexius.tools | J29: Esteban Guerrero(운영이사); WA +506 8873 5883; La Unión, Cartago | K29: 슈퍼마켓 장비(358품목): Dibal 라벨저울, 셀프계산대 | L29: 유통(슈퍼 장비) | M29: 상 | N29: 슈퍼마켓 납품, 저울은 여러 라인 중 하나 → 추가 브랜드 수용 가능 | O29: https://nexius.tools/catalogo/supermercados/
A30: 29 | B30: A | C30: 코스타리카 | D30: Romanas Azocar | E30: San José | F30: azocarcr.com | G30: info@azocarcr.com | H30: +506 2222-0000; WA 6224-0518 | I30: 기존 조사 (회사 사이트/디렉토리) | K30: 소매/라벨저울(Dibal), ISO17025 랩 | L30: 유통+교정 | M30: 상 | N30: 라벨저울 판매 + 공인 교정, 니카라과 동시 커버 | O30: https://www.azocarcr.com/product-page/etiquetadoras
A31: 30 | B31: B | C31: 코스타리카 | D31: Romanas HSR | E31: San José | F31: romanashsr.com | J31: 이메일 미공개 – romanashsr.com 문의폼 이용 | K31: Dibal 직수입 유통, Datalogic, 라벨저울 | L31: 수입/유통 | M31: 중 | N31: 라벨저울 전문이나 Dibal 전속 | O31: https://www.romanashsr.com/balanzas-etiquetadoras
A32: 31 | B32: B | C32: 코스타리카 | D32: Reproma | E32: Costa Rica | F32: reproma.com | G32: info@reproma.com | I32: reproma.com/contacto/ | J32: +506 2224-9491 | K32: CAS Corporation 공급사 페이지 보유 | L32: 유통 | M32: 중 | N32: CAS 연계, 상세 미확인 | O32: https://www.reproma.com/proveedor/cas-corporation/
A33: 32 | B33: C | C33: 코스타리카 | D33: Romanas Lacost S.A. | E33: Tibás, San José | G33: info@romanaslacost.com; multiservicioslacost@gmail.com | I33: eca.or.cr (인정기관 기록) | J33: +506 2248-0200 | K33: 판매·수리·교정(ISO17025) | L33: 서비스/딜러 | M33: 중하 | N33: 서비스 파트너 | O33: https://ilac.org/?p=126536
A34: 33 | B34: A | C34: 파나마 | D34: STH Panamá | E34: Panama City | F34: sthpanama.com | G34: ventas@sthpanama.com | H34: 343-5668 | I34: 기존 조사 (회사 사이트/디렉토리) | K34: 3nStar POS, 재정프린터, Aclas LS2X·Kretz 라벨저울 | L34: POS 딜러 | M34: 상 | N34: 중국/아르헨 라벨저울 이미 판매 → NETS 상위모델로 제안 | O34: https://sthpanama.com/contacto/
A35: 34 | B35: B | C35: 파나마 | D35: Grupo Único Internacional (CPG Panamá) | E35: Panama City | F35: cpgpanama.com | G35: ventas@cpgpanama.com; cpg507@outlook.com | H35: +507 217-1328; +507 6371-0258 | I35: cpgpanama.com/contactanos/ | J35: 주력은 라벨·롤지 – 저울 판매 근거 약함 | K35: 저울용 감열라벨, 영수증롤, 바코드, 저울 | L35: 유통(소모품) | M35: 중 | N35: 저울 라벨 판매 중 → 하드웨어+소모품 패키지 적합 | O35: https://www.cpgpanama.com/categoria-producto/etiquetas/etiquetas-termica-para-balanzas/
A36: 35 | B36: B | C36: 파나마 | D36: Posper Panamá | E36: Panama City | F36: posperpanama.com | G36: ventas@posperpanama.com; ventas2@posperpanama.com | I36: posperpanama.com/contactenos/ | J36: WA +507 6154-5057; +507 382-3700 | K36: 슈퍼마켓 POS, Datalogic 스캐너저울, 저울 교정 | L36: POS 딜러 | M36: 중상 | N36: 슈퍼마켓 POS 채널 | O36: https://posperpanama.com/soluciones-para-comercio-minorista-retail/
A37: 36 | B37: C | C37: 파나마 | D37: Industrial Scales of Panama, S.A. | E37: Panama City | G37: balanzas@cableonda.net | H37: 223-2231 | I37: 기존 조사 (회사 사이트/디렉토리) | K37: 저울 수리·교정 | L37: 서비스 | M37: 중하 | N37: 서비스/교정 파트너 | O37: https://sites.google.com/metrologiaindustrial.com/laboratoriometrologia/contactenos
A38: 37 | B38: C | C38: 파나마 | D38: CAS Latinoamérica S.A.S. (파나마) | E38: Panama City | F38: caslatinoamerica.com | G38: panama@caslatinoamerica.com | H38: +507 260-0114 | I38: 기존 조사 (회사 사이트/디렉토리) | K38: CAS 라벨저울 전 라인 | L38: CAS 유통 | M38: 하 | N38: 직접 경쟁사 채널 – 시장정보용 | O38: https://www.caslatinoamerica.com/
A39: 38 | B39: A | C39: 콜롬비아 | D39: BBG Colombia SAS (Básculas y Balanzas Guadalupe) | E39: Medellín 본사 + Bogotá, Cali, Barranquilla, Bucaramanga | F39: bbg.com.co | G39: ventas@basculasbbg.com; distribuidoresmedellin@basculasbbg.com; medellin@basculasbbg.com; info@basculasbbg.com | H39: (604) 557 8785; 311 214 2629; 316 655 0853 | I39: bbg.com.co/basculas/sp/contactenos | J39: 전국 PBX 601 745 7700; WA 317 705 1120 | K39: CAS 라벨저울(CL5200 등), Torrey, 정육장비 – 수입·제조·유통 | L39: 수입/유통(다지점) | M39: 상 | N39: 전국 멀티브랜드 대형 수입사, 라벨저울 판매 중, 딜러가격 운영 | O39: https://www.bbg.com.co/basculas/vp490/sp/balanza-etiquetadora-liquidadora-cas-cl-5200-p
A40: 39 | B40: B | C40: 콜롬비아 | D40: Capital Colombia | E40: Bogotá | F40: capitalcolombia.com | H40: (+57) 601 537 3270; 300 617 1853 | J40: 이메일 미공개 – WA 300 617 1853, 문의폼 capitalcolombia.com/sec-contactenos (주력은 라벨프린터·태블릿) | K40: POS HW: POS저울, 프린터저울, 가격표시기, 라벨프린터(CAS 등) | L40: POS 유통 | M40: 중 | N40: 소매·슈퍼 POS 채널, POS와 저울 번들 | O40: https://www.capitalcolombia.com/clases/colombia/bogota/hardware/balanzas_para_puntos_de_venta_balanzas_con_impresora_y_visores_de_precios_cc19c.php?marcaid=63
A41: 40 | B41: A | C41: 콜롬비아 | D41: Badecol (Balanzas de Colombia) | E41: Cali | F41: badecol.com | G41: ventas@badecol.com; comercial@badecol.com; exportaciones@badecol.com | I41: badecol.com | J41: 실제 위치 Cali; WA 315 492 7497 | K41: Dibal 라벨저울, 자체 기계식 저울, 디지털저울 수입 | L41: 제조+수입 | M41: 상 | N41: 유럽 라벨저울 수입·재판매, 수출입 개방적 | O41: https://www.badecol.com/collections/balanzas-dibal
A42: 41 | B42: B | C42: 콜롬비아 | D42: Importadora Torrey | E42: Bogotá / Cali / Medellín | F42: importadoratorrey.com | G42: bogota@importadoratorrey.com | I42: importadoratorrey.com/imtorrey/sp/contactenos | J42: WA +57 321 426 8429; CAS Latinoamérica와 주소 공유 | K42: Torrey LSQ 라벨저울, CAS CL5200 | L42: 수입 | M42: 중 | N42: BBG와 연관 가능성 – 확인 필요 | O42: https://www.importadoratorrey.com/imtorrey/vp40/sp/balanza-etiquetadora-torrey-lsq-guadalupe-bbg
A43: 42 | B43: B | C43: 콜롬비아 | D43: Básculas Bil | E43: Barranquilla, Cartagena, Valledupar | F43: basculasbil.com | G43: basculasbil@gmail.com; basculasyequiposbil@gmail.com; bilvalledupar@gmail.com | I43: basculasbil.com/contactanos/ | J43: Barranquilla 301 515 6015; Cartagena 304 663 6756 | K43: Dibal 터치 라벨저울, 라벨러 | L43: 딜러 | M43: 중 | N43: 고가 Dibal 판매 → NETS로 중가 공백 채우기 | O43: https://www.basculasbil.com/productos/colgante-dibal/
A44: 43 | B44: B | C44: 콜롬비아 | D44: Distriequipos Bogotá | E44: Bogotá | F44: distriequiposbogota.com | G44: ventas@distriequiposbogota.com; calidad@distriequiposbogota.com | I44: distriequiposbogota.com | J44: (601) 462 8269; 310 212 4694 | K44: Dibal Mistral 525, 식품장비 | L44: 딜러 | M44: 중 | N44: 식품장비+라벨저울 딜러 | O44: https://www.distriequiposbogota.com/producto/balanzas-colgante-con-memorias-e-impresora-marca-dibal-mistral-525-en-abs/
A45: 44 | B45: B | C45: 콜롬비아 | D45: Impoventas Colombia | F45: impoventas.com.co | G45: comercial1@impoventas.com.co; comercial2@impoventas.com.co; info@impoventas.com.co | I45: impoventas.com.co/contactenos/ | J45: Bosa Centro, Bogotá | K45: CAS CL-5200 | L45: 수입/딜러 | M45: 중 | N45: 정보 적음 | O45: https://www.impoventas.com.co/catalogo/balanza-etiquetadora-cas-cl-5200/
A46: 45 | B46: C | C46: 멕시코 | D46: Misrefris | E46: Mexico City | F46: misrefris.com | G46: contacto@misrefris.com; egarcia@misrefris.com | I46: misrefris.com | J46: ⚠ 콜롬비아가 아니라 멕시코시티 업체 (+52 55 5415 6805) | K46: Dibal M-525, 냉장설비 | L46: 딜러 | M46: 중하 | N46: 소규모 | O46: https://misrefris.com/producto/bascula-etiquetadora-dibal-m-525-5-t/
A47: 46 | B47: C | C47: 콜롬비아 | D47: CAS Latinoamérica | E47: Bogotá (+ 파나마) | F47: caslatinoamerica.com | G47: comercial2@caslatinoamerica.com; panama@caslatinoamerica.com; info@caslatinoamerica.com | H47: (57) 4-525 5994; 321 328 2020 | I47: caslatinoamerica.com; eldirectorio.co | J47: 실제 위치 Bogotá (Cra 24 #12b-54) | K47: CAS 라벨저울 | L47: CAS 지역유통 | M47: 하 | N47: 직접 경쟁사 채널 – 시장정보용 | O47: https://www.caslatinoamerica.com/caslatinoamerica/vp19/sp/balanza-etiquetadora-cas-modelo-cl5200-
A48: 47 | B48: A | C48: 에콰도르 | D48: La Competencia S.A. | E48: Ecuador | F48: competencia.com.ec | G48: ventas@competencia.com.ec; marketing@competencia.com.ec | I48: competencia.com.ec/contactanos/ | J48: WA 096 972 9361; (02) 382 7390 Quito | K48: DIGI 라벨저울(SM-320B, SM-5300 + 전자가격표), 보안·통신 | L48: 딜러/통합 | M48: 중상 | N48: DIGI 파는 리테일테크 통합사 → NETS 가성비 대안 | O48: https://competencia.com.ec/brand/4-digi
A49: 48 | B49: B | C49: 에콰도르 | D49: Electrónica Casio | E49: Guayaquil | F49: electronicacasio.com.ec | G49: ventasbalanzascas@electronicacasio.com.ec | H49: 04 390 7850; 099 719 2170 | I49: 기존 조사 (회사 사이트/디렉토리) | K49: CAS(CL5200, CL8000), Hiweigh – 슈퍼·바나나·새우·양계 | L49: 유통 | M49: 중 | N49: 라벨저울 채널 강하나 CAS 중심 | O49: https://electronicacasio.com.ec/
A50: 49 | B50: B | C50: 에콰도르 | D50: Ingelsoft | E50: Quito, Guayaquil | F50: ingelsoft.com | G50: info@ingelsoft.com | I50: ingelsoft.com | J50: Quito +593 2 255 0342; GYE +593 98 635 3635 | K50: 벤치/플랫폼/트럭 저울, 바코드 장비 | L50: 딜러/통합 | M50: 중 | N50: 저울+바코드 조합 적합 | O50: https://www.ingelsoft.com/catalogo-productos/balanzas/
A51: 50 | B51: C | C51: 에콰도르 | D51: Balanzas Vilanx | E51: Quito | F51: vilanx.ec | G51: contacto@vilanx.ec | H51: WA 098 148 1509 | I51: vilanx.ec | J51: WA 0981481509 | K51: Global CAS 공인 유통, 라벨저울, POS저울 | L51: 유통/딜러 | M51: 중하 | N51: CAS 공인 – 충돌 가능 | O51: https://www.vilanx.ec/balanzas-cas-ecuador-distribuidor/
A52: 51 | B52: C | C52: 에콰도르 | D52: Espinosa Páez S.A. | E52: Quito + Guayaquil, Cuenca, Manta | F52: espinosapaez.com | G52: espauio@espinosapaez.com | I52: espinosapaez.com | J52: 철자 특이 – 확인 필요; (02) 3948050 | K52: Mettler Toledo 대리(산업용) | L52: 브랜드 대리 | M52: 중하 | N52: Mettler 전속, 산업용 | O52: https://www.mt.com/ec/es/home.html
A53: 52 | B53: C | C53: 에콰도르 | D53: Balanzas Superior | E53: Guayaquil | G53: balanzasuperior@hotmail.com | I53: 2658-ec.all.biz (디렉토리) | J53: balanzasuperior.com; WA 0939242227 | K53: 산업용 저울 판매·서비스, Jadever | L53: 딜러/서비스 | M53: 중하 | N53: 산업용 중심 | O53: https://connectamericas.com/es/node/447678
A54: 53 | B54: A | C54: 도미니카공화국 | D54: Serpoca | E54: Santo Domingo | F54: serpoca.com.do | G54: ventas@serpoca.com.do; info@serpoca.com.do | I54: serpoca.com.do/contacto/ | J54: (809) 566-8732 | K54: 저울 + ISO17025 교정, 슈퍼마켓 솔루션(Supermercados Bravo 사례) | L54: 딜러/서비스/교정 | M54: 상 | N54: 슈퍼마켓 고객 보유, 브랜드 전속 미확인 | O54: https://serpoca.com.do/industria/supermercado/
A55: 54 | B55: B | C55: 도미니카공화국 | D55: Baserna (Balanzas y Servicios Nacionales) | E55: Santo Domingo Oeste | F55: balanzasnacionales.com | G55: serviciosbaserna@gmail.com | I55: balanzasnacionales.com/contactos/ | J55: 809-537-1136 | K55: CAS, Ohaus, Zemic | L55: 딜러/서비스 | M55: 중 | N55: 멀티브랜드 | O55: https://balanzasnacionales.com/sobre-nosotros/
A56: 55 | B56: B | C56: 도미니카공화국 | D56: Balanzas Industriales S.R.L. | E56: Santo Domingo | F56: balanzasindustriales.com | G56: info@balanzasindustriales.com; asistente@balanzasindustriales.com | I56: balanzasindustriales.com/contactos/ | J56: (809) 567-2194 | K56: CAS 공인, 슈퍼용 바코드 라벨저울, 교정·수리 | L56: 유통/서비스 | M56: 중 | N56: 슈퍼 라벨저울 사업 있음, CAS 충돌 가능 | O56: https://balanzasindustriales.com/
A57: 56 | B57: B | C57: 도미니카공화국 | D57: Balanza Del Caribe | E57: Santiago | F57: balanzadelcaribe.com | G57: balanzadelcaribe@gmail.com | I57: balanzadelcaribe.com | J57: 809-570-0207 | K57: 디지털 저울 판매·수리·교정 | L57: 딜러/서비스 | M57: 중 | N57: 시바오 지역 커버 | O57: https://balanzadelcaribe.com/
A58: 57 | B58: B | C58: 베네수엘라 | D58: Xacta Servicios C.A. (Industrias Metarmes) | E58: Caracas | F58: xacta.com.ve | G58: balanzas@xacta.com.ve | I58: xacta.com.ve | K58: 1985년부터 저울 제조, 글로벌 브랜드 독점대리, Cardinal 파트너 | L58: 제조/독점대리 | M58: 중 | N58: 기존 강자, 소매 라벨저울 라인 원할 수 있음 | O58: https://www.xacta.com.ve/
A59: 58 | B59: B | C59: 베네수엘라 | D59: Hitech 2023 | E59: Caracas (Chacao) | F59: hitech2023.com | G59: ventas@hitech2023.com | I59: hitech2023.com/contacto/ | J59: WA +58 424 234 0711 | K59: CAS CL3000 라벨저울 등 | L59: 딜러 | M59: 중 | N59: 리테일테크 딜러 | O59: https://www.hitech2023.com/producto/balanza-cas-etiquetadora-cl3000-30p-industrial/
A60: 59 | B60: B | C60: 베네수엘라 | D60: Batvenca | F60: batvenca.com | G60: ventas@batvenca.com | I60: batvenca.com/contactanos/ | J60: Valencia, Carabobo – 저울 취급 불확실 | K60: CAS CL5200N | L60: 딜러 | M60: 중 | N60: 제품 페이지 1개만 확인 | O60: https://batvenca.com/tienda/balanza-etiquetador-30kg-cas-cl-5200-n/
A61: 60 | B61: B | C61: 베네수엘라 | D61: Balanzas Lara | E61: Cabudare, Lara | G61: ventas@balanzaslara.com; servicios@balanzaslara.com | I61: facebook.com/p/Balanzas-Lara-100063934632793/ | J61: (0414) 350 1501 | K61: 계량장비 공급 (자칭 1위) | L61: 딜러/공급 | M61: 중 | N61: 전국 규모, 현황 미확인 | O61: https://www.machinetools.com/en/brands/balanzas-lara
A62: 61 | B62: C | C62: 베네수엘라 | D62: Balanzas CAS Venezuela | E62: Caracas (Petare) | F62: cas-ve.com | G62: casmen.venta@gmail.com; atccasmen@gmail.com; casmen@sinabrosa.com | H62: +58 212 213 9114; +58 424 165 5965 | I62: facebook.com/Casmen-Servicios-2140767302838691; empresasgrancaracas.com | J62: 실제 운영사 Servicios Casmen C.A.(casmen.com.ve), cas-ve.com 접속 불가. X @casmen_venta | K62: CAS 독점 대리, SENCAMER 인증 | L62: 독점유통 | M62: 하 | N62: CAS 전속 – 시장정보용 | O62: https://cas-ve.com/
A63: 62 | B63: B | C63: 푸에르토리코 | D63: SSM Foodservice Equipment / Scale Food Equipment & Systems | E63: San Juan, Guaynabo | G63: ssmfse@gmail.com; ssmhse@gmail.com | I63: ssmfoodservice.com; infopaginas | J63: Tel 787-763-2966 / 2965; FB SSMFoodservicePR | K63: 저울·식품장비 판매·서비스 (디렉토리) | L63: 딜러/서비스 | M63: 중 | N63: 식품소매 장비 채널 (NTEP 인증 필요) | O63: https://en.infopaginas.com/search/compare/anasco/scales
A64: 63 | B64: C | C64: 푸에르토리코 | D64: Super Business Machines (SBM) | E64: San Juan | F64: sbm-pr.com | G64: Infosbm5150@gmail.com | I64: facebook.com/SuperBusinessMachines | J64: 공식 문의폼 sbm-pr.com/en/Contact_Us; Tel 787-785-4310; 주소 Bayamón | K64: SAM4s POS + CAS 저울 독점, 1986년~ | L64: 독점유통(POS) | M64: 하 | N64: CAS 독점 | O64: https://www.sbm-pr.com/en/Home
A65: 64 | B65: C | C65: 푸에르토리코 | D65: PR Scale Services Inc | E65: Bayamón | G65: prscale@gmail.com | H65: 787-644-5415 | I65: facebook.com/PRScaleServicesInc; infopaginas | J65: Tel 787-798-9955 / 787-908-7711 | K65: 저울·금전등록기 서비스 | L65: 서비스 | M65: 중하 | N65: 서비스 파트너 | O65: https://www.buzzfile.com/business/PR-Scale-Services-Inc-787-644-5415
A66: 65 | B66: A | C66: 페루 | D66: Gufra Perú | E66: Lima (Puente Piedra) | F66: gufraperu.com | G66: ventas@gufraperu.com; administracion@gufraperu.com | I66: gufraperu.com/contacto/ | J66: +51 922 633 020; +51 933 395 701 | K66: CAS 라벨저울(CL-5200P 등), 산업용 저울 | L66: 유통(CAS) | M66: 상 | N66: 한국 CAS를 슈퍼·상점에 판매 중 → 세컨드라인/전환 | O66: https://gufraperu.com/balanzas-etiquetadoras/
A67: 66 | B67: A | C67: 페루 | D67: Invercorp Perú | E67: Lima (Barranco) | F67: invercorp-peru.com | G67: ventas@invercorp-peru.com | H67: (01) 764 5018; 957 570 011 | I67: invercorp-peru.com/contacto/ | K67: DIGI 라벨저울 수입(SM-110), 냉장·식품가공 장비 | L67: 수입 | M67: 상 | N67: DIGI 수입, 식품소매 납품 | O67: https://www.invercorp-peru.com/linea-de-pesaje/balanzas-etiquetadoras/
A68: 67 | B68: A | C68: 페루 | D68: Miyake | E68: Lima (Pueblo Libre) | F68: miyake.pe | G68: info@miyake.com.pe; asistente@miyake.com.pe | I68: miyake.pe/contacto/ | J68: 01-463-1325; 996295464; 997520612 (Pueblo Libre) | K68: CAS CL5200 판매·서비스 | L68: 딜러/서비스 | M68: 상 | N68: CAS 라벨저울 판매+서비스 | O68: https://www.miyake.pe/producto/balanzas-electronicas/balanzas-etiquetadoras/balanza-etiquetadora-cl-5200/
A69: 68 | B69: B | C69: 페루 | D69: La Casa de la Balanza Perú | E69: Lima, Arequipa | F69: lacasadelabalanzaperu.com | G69: ventas@lacasadelabalanzaperu.com | H69: 967 272 184 | I69: 기존 조사 (회사 사이트/디렉토리) | K69: DIGI, Teraoka 라벨저울 | L69: 딜러/소매 | M69: 중상 | N69: DIGI 취급, 2개 도시 매장 | O69: https://lacasadelabalanzaperu.com/balanza-digital-etiquetadora/
A70: 69 | B70: B | C70: 페루 | D70: Balanzas Precisur | E70: Lima (SMP), Arequipa | F70: balanzasprecisur.com | G70: ventas@balanzasprecisur.com | H70: (관련 balanzaslima.com 992 809 360) | I70: balanzasprecisur.com/contactenos/ | J70: WA +51 944 448 338 / +51 958 030 083 | K70: 슈퍼용 라벨저울 DIGI 수입, 서비스·교정 | L70: 수입/유통 | M70: 중 | N70: 수입+슈퍼 마케팅, balanzaslima.com과 같은 그룹 추정 | O70: https://balanzasprecisur.com/balanza-etiquetadora-para-supermercados/
A71: 70 | B71: B | C71: 페루 | D71: Balanzas PE | E71: Lima, Arequipa, Cusco | F71: balanzas.pe | G71: ventas@balanzas.pe | H71: (01) 734 54 34 | I71: balanzas.pe | J71: WA +51 992 558 338; Precisur와 동일 운영사 추정 | K71: 소매·도매 저울, 라벨저울 | L71: 딜러/소매 | M71: 중 | N71: 다지역 커버 | O71: https://balanzas.pe/balanzas-etiquetadoras/
A72: 71 | B72: B | C72: 온두라스 | D72: RR Inversiones | E72: Tegucigalpa / Managua | F72: rrinversiones.com | G72: info@rrinversiones.com | I72: rrinversiones.com | J72: ⚠ 페루가 아니라 온두라스/니카라과 업체로 확인 ((504) 2225-5535, (505) 2276-1795) | K72: DIGI SM-120 | L72: 딜러 | M72: 중 | N72: 라벨저울 판매 중 | O72: https://rrinversiones.com/producto/rr-116/
A73: 72 | B73: C | C73: 페루 | D73: Balanzas Calibra | E73: Lima | F73: balanzascalibra.com | H73: 964 381 357 | J73: 이메일 미공개 – WA 964381357 / 968705819 | K73: DIGI 저울, 전국 배송 | L73: 딜러 | M73: 중하 | N73: 소규모 리셀러 | O73: https://balanzascalibra.com/balanzas-digi/
A74: 73 | B74: C | C74: 페루 | D74: Pymatek | E74: Lima | F74: pymatek.pe | G74: ventas@pymatek.pe | I74: 기존 조사 (회사 사이트/디렉토리) | K74: Mettler Toledo 유통, 자동화 | L74: 유통 | M74: 중하 | N74: 산업/자동화 중심 | O74: https://www.pymatek.pe/manufacturers/440-mettler-toledo/
A75: 74 | B75: A | C75: 칠레 | D75: Tecno Rebas | E75: Santiago (La Cisterna) | F75: tecnorebas.cl | G75: ventas@tecnorebas.cl | H75: +56 9 8334 7255 / +56 9 3374 4246 | I75: 기존 조사 (회사 사이트/디렉토리) | K75: DIGI 가격계산·라벨저울, 금전등록기, 슬라이서, 쇼케이스 | L75: 딜러(업소장비) | M75: 상 | N75: 정육점·델리 납품, DIGI 취급 | O75: https://tecnorebas.cl/contactenos
A76: 75 | B76: A | C76: 칠레 | D76: Ing Métrica SpA | E76: Santiago (La Cisterna) | F76: ingmetrica.cl | G76: contacto@ingmetrica.cl | H76: +56 9 3030 4527; +56 44 3163412 | I76: 기존 조사 (회사 사이트/디렉토리) | K76: Dibal 공식 유통, Inspectra, 라벨·셀프저울 | L76: 독점유통 | M76: 상 | N76: 슈퍼·정육 라벨저울 전문 (Dibal 독점 충돌 가능) | O76: https://www.ingmetrica.cl/
A77: 76 | B77: A | C77: 칠레 | D77: Balanzas.cl | E77: Chile | F77: balanzas.cl | G77: contacto@balanzas.cl | I77: balanzas.cl | J77: +56 9 9831 9988 | K77: DIBAL·DIGI 공인 유통, 서비스 | L77: 유통 | M77: 상 | N77: 소매 라벨저울 전문 | O77: https://www.balanzas.cl/
A78: 77 | B78: B | C78: 칠레 | D78: Precision (precision.tech) | E78: Santiago (Huechuraba), 페루 지사 | F78: precision.tech/cl | G78: contactanos_chile@precision.tech | H78: +56 2 2422 6000 | I78: 기존 조사 (회사 사이트/디렉토리) | K78: Mettler Toledo 파트너(bCom-S 라벨저울), 실험장비 | L78: 유통 | M78: 중 | N78: 대형·리테일 서비스, Mettler 묶임 | O78: https://www.precision.tech/cl/productos/pesaje/pesaje-retail/balanzas-etiquetadoras
A79: 78 | B79: B | C79: 칠레 | D79: Maqequipos | E79: Santiago (Macul) | F79: maq-equipos.cl | G79: ventas@maq-equipos.cl | H79: +56 9 9334 0845 | I79: 기존 조사 (회사 사이트/디렉토리) | K79: Mettler 가격계산 저울(신품·리퍼), 식품장비 | L79: 딜러 | M79: 중 | N79: 식품소매 장비 딜러 | O79: https://www.maq-equipos.cl/41-balanza-mettler-toledo-tipificadoras
A80: 79 | B80: C | C80: 칠레 | D80: Empack | E80: Santiago (Las Condes) | G80: contacto@grupoempack.cl; consulta@empack.cl | I80: grupoempack.cl/en/contacto; all.biz | J80: (56-2) 2569 7500 | K80: Bizerba 상업용 저울 | L80: 딜러 | M80: 중하 | N80: 근거 약함 | O80: https://3856-cl.all.biz/balanza-mcg3293
A81: 80 | B81: C | C81: 칠레 | D81: Tecno Balanzas | E81: Santiago (La Cisterna) | F81: tecnobalanzas.cl | G81: ventas@tecnobalanzas.cl | I81: 기존 조사 (회사 사이트/디렉토리) | K81: 저울 | L81: 딜러 | M81: 중하 | N81: Tecno Rebas와 동일 주소 – 확인 | O81: https://tecnobalanzas.cl/
A82: 81 | B82: C | C82: 칠레 | D82: Systel Chile | E82: Chile | F82: systel-global.com/chile | G82: contacto@systel-global.com | I82: systel-global.com/chile/contacto/ | J82: 아르헨 본사 연락처만 존재 | K82: Systel(아르헨) 소매저울 | L82: 브랜드 지사 | M82: 하 | N82: 경쟁 브랜드 – 시장정보용 | O82: https://systel-global.com/chile/
A83: 82 | B83: A | C83: 볼리비아 | D83: CAS – Computer & Sensors SRL | E83: La Paz | F83: casbolivia.com | G83: info@cas-bo.com; ventas@cas-bo.com | I83: casbolivia.com/contacto | J83: 현 사이트 casbolivia.com; +591-2-2414477; 76232262 | K83: CAS 상업용 저울, CL-7200·CL-5200 | L83: CAS 유통 | M83: 상 | N83: 볼리비아 CAS 라벨저울 채널 → 전환 타깃 | O83: https://gnb.com.bo/guia/Comercio,-importaciones-y-exportaciones/Balanzas-y-basculas.html
A84: 83 | B84: A | C84: 볼리비아 | D84: Exim SRL | E84: Santa Cruz | F84: exim.com.bo | G84: info@exim.com.bo | H84: +591 3 3336363; +591 69059233 | I84: 기존 조사 (회사 사이트/디렉토리) | K84: 상업용·정밀·플랫폼·트럭 저울, 농산업 | L84: 수입/유통 | M84: 중상 | N84: 상업용 포함 폭넓은 계량 라인 | O84: https://exim.com.bo/contacto/
A85: 84 | B85: B | C85: 볼리비아 | D85: Pesotodo SRL | E85: Santa Cruz | F85: pesotodo.com | G85: ventas@pesotodo.com | H85: +591 75646170 | I85: 기존 조사 (회사 사이트/디렉토리) | K85: Toledo do Brasil, OHAUS 대리, 수입·서비스·교정 | L85: 수입/서비스 | M85: 중상 | N85: 등록 수입사 + 서비스 역량 | O85: http://boliviapymes.com/ficha/pesotodo-srl-77664
A86: 85 | B86: B | C86: 볼리비아 | D86: Zelada Precision SRL | E86: Santa Cruz | G86: gzelada@zeladaprecision.com | H86: 3480055 (디렉토리) | I86: 1596-bo.all.biz | J86: +591 3 348-0055 | K86: 계량장비·저울 SW, 자체 공장 | L86: 제조/딜러 | M86: 중 | O86: https://amarillas.bo/empresa/zelada-precision-srl
A87: 86 | B87: C | C87: 볼리비아 | D87: Métrica Ltda | E87: La Paz | F87: metrica.com.bo | G87: info@metrica.com.bo; comercial@metrica.com.bo | I87: metrica.com.bo/inicio/nosotros | J87: WA +591 71538792 | K87: Mettler Toledo 산업·트럭저울 | L87: 유통(산업) | M87: 하 | N87: 산업용 중심 | O87: https://www.mt.com/bo
A88: 87 | B88: A | C88: 아르헨티나 | D88: Grupo Hasar (Hasar Sistemas SRL) | E88: Buenos Aires (Ricardo Rojas) | F88: compania.grupohasar.com | G88: info@hasar.com | H88: +54 11 4117 8900 | I88: compania.grupohasar.com | J88: 문의폼 sistemas.grupohasar.com/contacto/; ventas@grupohasar.com(약한 출처) | K88: DIGI SM 라벨저울 자체브랜드, 재정프린터, POS; INTI 승인 경험 | L88: 수입/브랜드(POS) | M88: 상 | N88: 외산 라벨저울 수입+INTI 승인 경험, SM-5300 단종 → 대체품 필요 가능 | O88: https://compania.grupohasar.com/categoria-producto/balanzas/
A89: 88 | B89: B | C89: 베네수엘라 | D89: Laser Print Soluciones | E89: Caracas (Chacao)/Miranda | F89: laserprintsoluciones.com | G89: ventas@laserprintsoluciones.com; info@laserprintsoluciones.com | I89: laserprintsoluciones.com/contacto/ | J89: ⚠ 아르헨티나가 아니라 베네수엘라 업체 (WA +58 414 3235239) | K89: CAS CL-5200P, Aclas LS2 | L89: 딜러 | M89: 상(확인 시) | N89: POS·재정프린터·토너 업체, CAS CL-5200P·Aclas 판매 페이지 있음 | O89: https://www.laserprintsoluciones.com/producto/balanza-etiquetadora-cas-cl-5200p/
A90: 89 | B90: B | C90: 아르헨티나 | D90: FDC Soluciones SRL | E90: Argentina | F90: fdcsolucionessrl.com | G90: info@fdcsoluciones.com | I90: facebook.com/fdcsolucionessrl/ | J90: Rafaela, Santa Fe | K90: Hasar/Digi, Kretz, Systel 저울, Zebra 라벨, 재정프린터 | L90: POS/라벨링 통합 | M90: 중 | N90: POS+라벨저울 판매 | O90: https://www.fdcsolucionessrl.com/equipos/balanzas
A91: 90 | B91: B | C91: 아르헨티나 | D91: Posvent | E91: Argentina | F91: posventar.com | G91: info@posventar.com | I91: posvent.com.ar | J91: WA +54 9 11 6760-4389; Lomas de Zamora | K91: Systel, Kretz 저울, POS | L91: 딜러/POS 통합 | M91: 중 | N91: POS 통합사 | O91: https://posventar.com/productos/balanzas-electronicas
A92: 91 | B92: B | C92: 아르헨티나 | D92: Balanzas Kyaserv | E92: Argentina | F92: balanza.com.ar | G92: info@kyaserv.com.ar; info@balanza.com.ar | I92: kyaserv.com.ar/web/contacto/ | J92: WA +54 9 11 6516-0955 | K92: Systel, Kretz, Moretti; INTI 검정 서비스 | L92: 딜러+서비스 | M92: 중 | N92: 검정·AS 역량 | O92: https://balanza.com.ar/web/balanzas-comerciales/
A93: 92 | B93: B | C93: 아르헨티나 | D93: Digital Crams | E93: Argentina | F93: dcrams.com.ar | G93: info@dcrams.com.ar | I93: dcrams.com.ar/contacto/ | J93: WA 11 6355 3307; Vicente López | K93: Kretz 라벨저울(Report LT/NX) | L93: 딜러/유통 | M93: 중 | N93: 라벨저울 리셀러, Kretz 묶임 | O93: https://dcrams.com.ar/productos/balanzas
A94: 93 | B94: B | C94: 아르헨티나 | D94: STEC Soluciones Tecnológicas | E94: Argentina | F94: stec.com.ar | G94: ventas@stec.com.ar | I94: stec.com.ar/pages/contact | J94: Florida 716, CABA | K94: Kretz, Systel | L94: 딜러 | M94: 중 | N94: 현지 브랜드 위주 | O94: https://www.stec.com.ar/collections/kretz
A95: 94 | B95: C | C95: 아르헨티나 | D95: Casa Schettini | E95: Córdoba | F95: casaschettini-shop.com | G95: ventas@casaschettini.com | I95: facebook.com/casaschettinicba/ | J95: WA 351 399 9579 | K95: Systel, Kretz, 라벨프린터, 매장장비 | L95: 딜러/소매 | M95: 중하 | N95: 소매업체 | O95: https://casaschettini-shop.com/balanzas/
A96: 95 | B96: C | C96: 아르헨티나 | D96: Micro Power | E96: Argentina | F96: micro-power.com.ar | G96: consultas@micro-power.com.ar | I96: micro-power.com.ar | J96: Berazategui | K96: Systel, Moretti, Digi, Kretz 서비스 | L96: 서비스 | M96: 중하 | N96: 서비스 파트너 | O96: https://www.micro-power.com.ar/
A97: 96 | B97: C | C97: 아르헨티나 | D97: Bizerba Argentina S.A. | E97: Villa Martelli (Prov. BA) | G97: ar_ventas@bizerba.com | I97: guiademantenimiento.com (디렉토리) | J97: Villa Martelli; (011) 4575-0000 | K97: Bizerba 자회사 | L97: 경쟁사 자회사 | M97: 하 | N97: 경쟁사 | O97: https://www.inti.gob.ar/assets/uploads/files/metrologia-legal/empresas/reparadoras/40/040-BizerbaArg.pdf
A98: 97 | B98: A | C98: 우루과이 | D98: Baudin Equipamientos | E98: Canelones / Montevideo | F98: baudinequipamientos.com | G98: ventas@baudinequipamientos.com; gerencia@baudinequipamientos.com | I98: baudinequipamientos.com/contacto/ | J98: WA 098 193 160 | K98: Dibal(LATU 승인), Systel, Kuma 등, 할부 판매 | L98: 수입/딜러+서비스 | M98: 상 | N98: LATU 승인 수입 라벨저울 판매 + 자체 서비스 | O98: https://baudinequipamientos.com/marca/dibal/
A99: 98 | B99: A | C99: 우루과이 | D99: Ser-Tec | E99: Montevideo | F99: ser-tec.com.uy | G99: ventas@ser-tec.com.uy; info@ser-tec.com.uy | H99: Tel. 2402 8972 | I99: ser-tec.com.uy | J99: 098 649 559 | K99: 저울·금전등록기 수입·판매·서비스(80년대~), Kretz 대리, 전자세금계산서 | L99: 수입/딜러+서비스 | M99: 상 | N99: POS 고객 + LATU 경험 | O99: https://www.ser-tec.com.uy/
A100: 99 | B100: B | C100: 우루과이 | D100: Balanzas Larynco | E100: Montevideo | F100: balanzaslarynco.com.uy | G100: reparaciones@balanzaslarynco.com.uy | H100: 2508 8189 | I100: 기존 조사 (회사 사이트/디렉토리) | K100: Systel, Sipel, Flintec, 판매·서비스 | L100: 딜러+서비스 | M100: 중 | N100: 서비스 중심, 신규 브랜드 가능 | O100: https://www.balanzaslarynco.com.uy/
...

Sheet 국가별 진입 노트
A1: 국가 | B1: 인증/규제 (법정계량) | C1: 주요 경쟁 브랜드 | D1: 비고/불확실성
A2: 멕시코 | B2: NOM-010-SCFI-1994 + DGN 모델승인 등록, PROFECO 초기·정기 검정(홀로그램) | C2: Torrey(현지), Rhino, DIGI(Mexba), CAS(바하 지역 POS딜러), Bizerba/Dibal/Mettler(체인) | D2: NOM-EM-020-SE-2020 적용 여부 미확인
A3: 과테말라 | B3: DIACO·CENAME 점검 / 소매저울 형식승인 규정 미확인 → OIML R76 + 현지 교정이 실무 요건으로 추정 | C3: CAS(엘살바도르 독점사 경유), Torrey | D3: 불확실
A4: 엘살바도르 | B4: 소비자보호청 점검 시 연 1회 공인업체 교정증명서·스티커 필요 | C4: CAS(중미 북부 독점), Rhino/Vinson/Torrey
A5: 온두라스 | B5: SDE 소비자보호국(Decree 24-2008) 정확도 점검, 형식승인 제도 미확인 | C5: Torrey, CAS, Rice Lake(산업) | D5: 2019년 자료
A6: 니카라과 | B6: 규정 미조사 – 현지 수입사·MIFIC 확인 필요 | C6: CAS, Kretz, Ishida, Rice Lake
A7: 코스타리카 | B7: LACOMET(MEIC) 법정계량 점검, RTCR 존재 여부 미확인 | C7: Dibal 압도적, CAS(Reproma)
A8: 파나마 | B8: ACODECO 점검, DGNTI-COPANIT 37-2002 (현행 여부 확인), POS는 DGI 전자세금계산서 필요 | C8: CAS 직영 사무소, Aclas·Kretz(POS딜러), Datalogic
A9: 콜롬비아 | B9: SIC 비자동저울 기술규정(Res. 33187/2023) – OIML 형식시험 인증서 + 적합성 선언 + SIMEL 등록 필수 | C9: CAS 매우 강함, Dibal 2위, DIGI·Mettler(대형체인) | D9: 2026년 개정안 공포 여부 미확인
A10: 에콰도르 | B10: INEN 기술규정/INEN-1 인증(VUE/Ecuapass) – 저울 해당 RTE 번호 확인 필요. 달러 경제(환리스크 낮음) | C10: CAS 지배적(위조품 유통), DIGI, Mettler
A11: 도미니카공화국 | B11: INDOCAL 법정계량(콜마도 연1회 점검), Pro Consumidor 합동점검. 모델승인 인증 존재 추정 – 확인 | C11: CAS(Balanzas Industriales), Mettler | D11: 주요 체인: Sirena, Nacional, Jumbo, Bravo
A12: 베네수엘라 | B12: SENCAMER 현지 인증 필요(외국 인증 불인정 보고). 외환통제·제재 심사 – 선금/확인 L/C 권장 | C12: CAS 독점대리, Xacta(현지제조) | D12: 결제 리스크 높음
A13: 푸에르토리코 | B13: 미국 영토 – NTEP 인증(NIST HB44) 필수, DACO 검사, FCC·UL/ETL 필요 | C13: CAS 독점(SBM), Hobart, Mettler, Bizerba, DIGI | D13: NTEP 없으면 판매 불가
A14: 쿠바 | B14: 국영기업/Mipymes 경유, 장기 외상·미수 위험, 미국 금수조치로 USD 결제 곤란 | C14: - | D14: 파나마/스페인 무역상 경유만 현실적, 리드 미조사
A15: 페루 | B15: INACAL R.D. 006-2018: 100kg 이하 상거래 저울 모델승인+초기/정기 검정(NMP 003:2009=OIML R76). 외국 승인서 인정 가능 → OIML R76 인증서 매우 유리. 한-페루 FTA(2011) | C15: CAS(Gufra, Miyake), DIGI/Teraoka, Mettler | D15: HS 8423.81 무관세 여부 확인 필요
A16: 칠레 | B16: 상거래 저울 의무 형식승인 불명확, 어댑터 SEC 전기안전 인증 가능성 – INN/SEC 확인. 한-칠레 FTA(2004) 대부분 무관세 | C16: Dibal, DIGI, Mettler, Systel – CAS 채널 미확인 = 한국 브랜드 기회
A17: 볼리비아 | B17: DS 5103(2024) + RM 044/2024: 통관 시 IBMETRO 증명서(CRTM 모델승인, CCRT 적합성) 필수 – 첫 선적 전 준비. FTA 없음 | C17: CAS, Toledo do Brasil, Mettler, Systel | D17: 시장 작음, 최대 체인 Hipermaxi
A18: 아르헨티나 | B18: Ley 19.511: 현지 수입사가 INTI 시험 → 상무부 모델승인 + 최초검정, RUMP 등록 (balanzas@inti.gob.ar). 메르코수르 공동관세, 수입·외환 규정 수시 변경 | C18: Systel·Kretz(현지) 지배적, DIGI(Hasar), Bizerba, Mettler | D18: 통관사(despachante) 확인 필요
A19: 우루과이 | B19: LATU 법정계량 승인·관리 필수, 메르코수르 공동관세 | C19: Dibal(Baudin), Systel, Kretz(Ser-Tec), Mettler | D19: 주요 체인: Disco/Devoto/Géant, Tienda Inglesa
A20: 파라과이 | B20: INTN-ONM 정기검정 봉인(연 1회) 필수, 수입 모델승인 여부 미확인 | C20: Kretz, Systel, DINA(Balpar), Dibal | D20: Balpar가 사실상 관문
A21: 적도기니 | B21: CEMAC 회원국, 법정계량 제도 불명확, 현지 유통사 미발견 | C21: - | D21: 스페인 딜러 또는 카메룬/가봉 유통사 경유 – 우선순위 최하
A23: 공통 TIP
A24: • | B24: OIML R76 인증서(가능하면 MID/OIML MAA)를 확보하면 페루·콜롬비아·볼리비아 등 형식승인이 크게 쉬워짐
A25: • | B25: CAS(한국 경쟁사)가 중남미 전역에 깔려 있음 → 'CAS 대비 가격/기능/라벨 소프트웨어 우위' 비교표를 준비
A26: • | B26: 스페인어 카탈로그·라벨 SW UI·매뉴얼 필수, 저울 라벨 소모품 공급 조건도 함께 제안
A27: • | B27: 결제: 베네수엘라·쿠바·아르헨티나는 선금 또는 확인 L/C
